myfuncx/__init__.py
myfuncx/client.py
myfuncx/json_manager.py
myfuncx-0.0.1.dist-info/LICENSE
myfuncx-0.0.1.dist-info/METADATA
myfuncx-0.0.1.dist-info/WHEEL
myfuncx-0.0.1.dist-info/top_level.txt
myfuncx-0.0.1.dist-info/RECORD
